{"type":"routine","v":1,"routine":{"id":"ohhmvj1a","name":"Full body (intermedios)","clientId":"","weeks":6,"startDate":"","notes":"Priorizar tiempo de trabajo efectivo","days":[{"day":1,"exercises":[{"exerciseId":"iyx0i5yn","sets":"1","reps":"5 minutos","weight":"","rest":"60s","notes":""},{"exerciseId":"6zpm2iru","sets":"4","reps":"8 - 10","weight":"","rest":"60s","notes":""},{"exerciseId":"qq4f5t4p","sets":"3","reps":"10 - 12","weight":"","rest":"60s","notes":""},{"exerciseId":"xas35zev","sets":"3","reps":"12 - 15","weight":"","rest":"60s","notes":""},{"exerciseId":"5vgy7yel","sets":"3","reps":"10 - 12","weight":"(30° de inclinacion del banco)","rest":"60s","notes":""},{"exerciseId":"wybdrvih","sets":"3","reps":"12 - 15","weight":"","rest":"60s","notes":""},{"exerciseId":"akyllfex","sets":"3","reps":"45s","weight":"","rest":"30s","notes":""},{"exerciseId":"ttvaafn1","sets":"3","reps":"45 s ","weight":"","rest":"30s","notes":""}]},{"day":2,"exercises":[{"exerciseId":"imkaw38k","sets":"1","reps":"5 minutos","weight":"","rest":"60s","notes":""},{"exerciseId":"8iyl29xw","sets":"4","reps":"8 - 12","weight":"","rest":"60s","notes":""},{"exerciseId":"ilcunyqh","sets":"3","reps":"10 - 12","weight":"","rest":"60s","notes":""},{"exerciseId":"ebtm5ei2","sets":"3","reps":"10 - 12","weight":"","rest":"60s","notes":""},{"exerciseId":"f0eppo0v","sets":"3","reps":"12 - 15","weight":"","rest":"60s","notes":""},{"exerciseId":"ab9gkqza","sets":"3","reps":"12 - 15","weight":"","rest":"60s","notes":""},{"exerciseId":"vo3xy1ge","sets":"3","reps":"8 - 10 ","weight":"","rest":"60s","notes":""}]},{"day":3,"exercises":[{"exerciseId":"tec7knby","sets":"1","reps":"5 minutos","weight":"","rest":"60s","notes":""},{"exerciseId":"0zxn2shl","sets":"3","reps":"10 - 12","weight":"","rest":"60s","notes":""},{"exerciseId":"wwyorsjn","sets":"3","reps":"10","weight":"Inclinacion del banco (30°  - 45°)","rest":"60s","notes":""},{"exerciseId":"oo91onqa","sets":"3","reps":"10 - 12","weight":"","rest":"60s","notes":""},{"exerciseId":"i4p5dyix","sets":"3","reps":"10","weight":"","rest":"60s","notes":""},{"exerciseId":"5vgy7yel","sets":"3","reps":"10","weight":"","rest":"60s","notes":""},{"exerciseId":"qv66woaz","sets":"3","reps":"10 - 12","weight":"","rest":"60s","notes":""},{"exerciseId":"50td1ffr","sets":"3","reps":"10 - 12","weight":"","rest":"60s","notes":""},{"exerciseId":"n1kczb4b","sets":"3","reps":"15 - 20","weight":"","rest":"60s","notes":""},{"exerciseId":"rytrk439","sets":"3","reps":"45 s ","weight":"","rest":"30s","notes":""}]},{"day":4,"exercises":[]},{"day":5,"exercises":[]},{"day":6,"exercises":[]},{"day":7,"exercises":[]}]},"client":null,"exercises":[{"id":"iyx0i5yn","name":"Bicicleta estática","muscle":"Cardio","equipment":"Máquina","desc":"Mantén cadencia constante, ajusta resistencia.","gif":"https://fitcron.com/wp-content/uploads/2021/03/21381301-Stationary-Bike-Run-version-3_Cardio_720.gif"},{"id":"6zpm2iru","name":"Sentadilla con barra","muscle":"Pierna","equipment":"Barra","desc":"Barra en trapecios, baja hasta paralelo y sube.","gif":"https://fitcron.com/wp-content/uploads/2021/04/00631301-Barbell-Narrow-Stance-Squat_Thighs_720.gif"},{"id":"qq4f5t4p","name":"Press militar con mancuernas","muscle":"Hombro","equipment":"","desc":"Utilizar banco","gif":"https://fitcron.com/wp-content/uploads/2021/04/04261301-Dumbbell-Standing-Overhead-Press_shoulder_720.gif"},{"id":"xas35zev","name":"Leg extension","muscle":"Pierna","equipment":"Máquina","desc":"","gif":"https://fitnessprogramer.com/wp-content/uploads/2021/02/LEG-EXTENSION.gif"},{"id":"5vgy7yel","name":"Aperturas con mancuernas","muscle":"Pecho","equipment":"Mancuernas","desc":"Brazos ligeramente flexionados, abre y cierra describiendo un arco.","gif":"https://fitcron.com/wp-content/uploads/2021/03/03081301-Dumbbell-Fly_Chest-FIX_720.gif"},{"id":"wybdrvih","name":"Extensión de tríceps en polea","muscle":"Brazo","equipment":"Polea","desc":"Codos pegados, extiende los antebrazos hacia abajo.","gif":"https://fitcron.com/wp-content/uploads/2021/04/02411301-Cable-Triceps-Pushdown-V-bar-attachment_Upper-Arms_720.gif"},{"id":"akyllfex","name":"Plancha frontal","muscle":"Core","equipment":"Peso corporal","desc":"Mantén el cuerpo recto en apoyo de antebrazos.","gif":"https://fitcron.com/wp-content/uploads/2021/04/04631301-Front-Plank_waist-FIX_720.gif"},{"id":"ttvaafn1","name":"Plancha lateral","muscle":"Core","equipment":"Peso corporal","desc":"Apoyo lateral en codo, cadera elevada.","gif":"https://fitcron.com/wp-content/uploads/2021/04/07151301-Side-Plank-m_Waist_720.gif"},{"id":"imkaw38k","name":"Remadora","muscle":"Cardio","equipment":"Máquina","desc":"","gif":"https://media0.giphy.com/media/v1.Y2lkPTZjMDliOTUyZnFmeWpsNmc2azFmMm0wMHJxZzNwNjRmNmRzZnNteWFjeWx1ZXpjZCZlcD12MV9naWZzX3NlYXJjaCZjdD1n/12bgKWqBoAMbbG/giphy.gif"},{"id":"8iyl29xw","name":"Remo con barra","muscle":"Espalda","equipment":"Barra","desc":"Tronco inclinado 45°, lleva la barra al abdomen sin balanceos.","gif":"https://fitcron.com/wp-content/uploads/2021/04/00271301-Barbell-Bent-Over-Row_Back-FIX_720.gif"},{"id":"ilcunyqh","name":"Hip thrust","muscle":"Glúteo","equipment":"Barra","desc":"Apoya espalda en banco, sube cadera contrayendo glúteos.","gif":"https://fitnessprogramer.com/wp-content/uploads/2021/02/Barbell-Hip-Thrust.gif"},{"id":"ebtm5ei2","name":"Jalon al pecho","muscle":"Espalda","equipment":"Máquina","desc":"","gif":"https://static.wixstatic.com/media/c94d75_33fa8ffcfe94421586595b5f05e83c64~mv2.gif"},{"id":"f0eppo0v","name":"Curl alterno con mancuernas","muscle":"Brazo","equipment":"Mancuernas","desc":"Alterna brazos, gira la muñeca al subir.","gif":"https://eresfitness.com/wp-content/uploads/2019/05/Curl-de-biceps.gif"},{"id":"ab9gkqza","name":"Curl femoral con banda elastica","muscle":"Pierna","equipment":"","desc":"Atar  banda elastica (a rack u otro elemento que no se mueva)","gif":"https://i.makeagif.com/media/12-17-2025/YW9LnD.gif"},{"id":"vo3xy1ge","name":"Dear bug","muscle":"Core","equipment":"Peso corporal","desc":"","gif":"https://media2.giphy.com/media/v1.Y2lkPTZjMDliOTUybWF0bm0yMGhzOHUxdmpnNXlyY29odHNsZnB4N2dhZW11MmI1aDd0ZSZlcD12MV9naWZzX3NlYXJjaCZjdD1n/aIyZ9Ra6pyo5ZOHQsm/giphy.gif"},{"id":"tec7knby","name":"Caminadora — trote","muscle":"Cardio","equipment":"Caminadora","desc":"Trote suave a moderado.","gif":"https://i.pinimg.com/originals/37/1a/d4/371ad4137ee381e717e5e65113ffe4b9.gif"},{"id":"0zxn2shl","name":"Estocadas bulgaras","muscle":"Pierna","equipment":"","desc":"","gif":"https://i.pinimg.com/originals/20/8a/40/208a40f1323d4ef64b5e4635434ddedb.gif"},{"id":"wwyorsjn","name":"Press inclinado con mancuernas","muscle":"Pecho","equipment":"Mancuernas","desc":"Banco a 30-45°. Empuja desde los hombros sin chocar las mancuernas arriba.","gif":"https://fitcron.com/wp-content/uploads/2021/03/03241301-Dumbbell-Incline-Palm-in-Press_Chest_720.gif"},{"id":"oo91onqa","name":"Remo con polea baja","muscle":"Espalda","equipment":"Polea","desc":"","gif":"https://fitcron.com/wp-content/uploads/2021/04/38591301-Cable-Bent-Over-Row_Back_720.gif"},{"id":"i4p5dyix","name":"Elevaciones laterales","muscle":"Hombro","equipment":"Mancuernas","desc":"Eleva las mancuernas hasta la altura de los hombros.","gif":"https://static.wixstatic.com/media/c94d75_86585c1261ef4d0aaa235280b21a560d~mv2.gif"},{"id":"qv66woaz","name":"Curl martillo","muscle":"Brazo","equipment":"Mancuernas","desc":"Agarre neutro, sube manteniendo las palmas enfrentadas.","gif":"https://fitcron.com/wp-content/uploads/2021/04/02981301-Dumbbell-Cross-Body-Hammer-Curl_Forearms_720.gif"},{"id":"50td1ffr","name":"Press francés","muscle":"Brazo","equipment":"Barra","desc":"Acostado, baja la barra detrás de la cabeza flexionando codos.","gif":"https://fitcron.com/wp-content/uploads/2021/04/03521301-Dumbbell-Neutral-Grip-Bench-Press_Upper-Arms_720.gif"},{"id":"n1kczb4b","name":"Elevación de talón de pie","muscle":"Pierna","equipment":"Máquina","desc":"Sube y baja en puntas de pie.","gif":"https://api.smartworkout.app/asset/image/01f86161-5bb5-4bec-bad0-13e96076fd37"},{"id":"rytrk439","name":"Crunch abdominal","muscle":"Core","equipment":"Peso corporal","desc":"Acostado, levanta los hombros contrayendo el abdomen.","gif":"https://fitcron.com/wp-content/uploads/2024/05/00031301-air-bike-m_waist_FIX_720.gif"}],"skippedHeavy":0,"sharedAt":1778797974036,"sc":{"gt":"~TmhXOTVCQ0tRV1paNEtXQmV3SGwxTWRvZU9rNFhocWRwUENVSEhWY1RBdXJGODRSaEFCckR1UnhXRlZfcjNMWkdBY1FPNzdwMEFPR1JSQ0MxMV90YXBfYnVodGln","gr":"ultrasport19-boop/APP-RUTINAS1","gb":"main","bt":"","bd":"","bu":"https://ultrasport19-boop.github.io/APP-RUTINAS1/"}}